rdsa_utils/__init__.py
rdsa_utils/exceptions.py
rdsa_utils/logging.py
rdsa_utils/test_utils.py
rdsa_utils/typing.py
rdsa_utils/validation.py
rdsa_utils/cdp/__init__.py
rdsa_utils/cdp/helpers/__init__.py
rdsa_utils/cdp/helpers/hdfs_utils.py
rdsa_utils/cdp/helpers/impala.py
rdsa_utils/cdp/helpers/s3_utils.py
rdsa_utils/cdp/io/__init__.py
rdsa_utils/cdp/io/input.py
rdsa_utils/cdp/io/output.py
rdsa_utils/cdp/io/pipeline_runlog.py
rdsa_utils/gcp/__init__.py
rdsa_utils/gcp/helpers/__init__.py
rdsa_utils/gcp/helpers/gcp_utils.py
rdsa_utils/gcp/io/__init__.py
rdsa_utils/gcp/io/inputs.py
rdsa_utils/gcp/io/outputs.py
rdsa_utils/helpers/__init__.py
rdsa_utils/helpers/pyspark.py
rdsa_utils/helpers/python.py
rdsa_utils/helpers/pyspark_log_parser/__init__.py
rdsa_utils/helpers/pyspark_log_parser/ec2_pricing.py
rdsa_utils/helpers/pyspark_log_parser/init_aws_ec2_db.py
rdsa_utils/helpers/pyspark_log_parser/parser.py
rdsa_utils/helpers/pyspark_log_parser/pyspark_log_report_template.ipynb
rdsa_utils/helpers/pyspark_log_parser/report.py
rdsa_utils/helpers/pyspark_log_parser/data/__init__.py
rdsa_utils/helpers/pyspark_log_parser/data/ec2_pricing.db
rdsa_utils/io/__init__.py
rdsa_utils/io/config.py
rdsa_utils/io/input.py
rdsa_utils/io/output.py
rdsa_utils/methods/__init__.py
rdsa_utils/methods/averaging_methods.py
rdsa_utils-0.16.0.dist-info/licenses/LICENSE
rdsa_utils-0.16.0.dist-info/METADATA
rdsa_utils-0.16.0.dist-info/WHEEL
rdsa_utils-0.16.0.dist-info/top_level.txt
rdsa_utils-0.16.0.dist-info/RECORD
