Metadata-Version: 2.4
Name: rdsa-utils
Version: 0.16.0
Summary: A suite of PySpark, Pandas, and general pipeline utils for Reproducible Data Science and Analysis (RDSA) projects.
Home-page: https://github.com/ONSdigital/rdsa-utils
Author: Reproducible Data Science & Analysis, ONS
Author-email: RDSA.Support@ons.gov.uk
Classifier: Programming Language :: Python :: 3
Classifier: Programming Language :: Python :: 3.8
Classifier: Programming Language :: Python :: 3.9
Classifier: Programming Language :: Python :: 3.10
Classifier: Programming Language :: Python :: 3.11
Classifier: Programming Language :: Python :: 3.12
Classifier: Programming Language :: Python :: 3.13
Classifier: License :: OSI Approved :: MIT License
Classifier: Operating System :: OS Independent
Requires-Python: <3.14,>=3.8
License-File: LICENSE
Requires-Dist: cloudpathlib[gs]>=0.15.1
Requires-Dist: humanfriendly>=9.1
Requires-Dist: more-itertools>=9.0.0
Requires-Dist: pandas
Requires-Dist: pydantic>=2.6.2
Requires-Dist: pyyaml>=6.0.1
Requires-Dist: tomli>=2.0.1
Requires-Dist: google-cloud-bigquery>=3.17.2
Requires-Dist: google-cloud-storage>=2.14.0
Requires-Dist: boto3>=1.34.103
Requires-Dist: codetiming
Requires-Dist: standard-distutils; python_version >= "3.12"
Requires-Dist: xlsxwriter
Requires-Dist: openpyxl
Requires-Dist: papermill
Requires-Dist: nbconvert
Requires-Dist: matplotlib
Provides-Extra: dev
Requires-Dist: bump2version>=1.0.0; extra == "dev"
Requires-Dist: pre-commit>=2.6.0; extra == "dev"
Requires-Dist: ruff>=0.0.270; extra == "dev"
Requires-Dist: chispa>=0.9.2; extra == "dev"
Requires-Dist: coverage[toml]>=7.1.0; extra == "dev"
Requires-Dist: pytest<8.0.0,>=7.1.0; extra == "dev"
Requires-Dist: pytest-cov>=4.0.0; extra == "dev"
Requires-Dist: pytest-lazy-fixture>=0.6.0; extra == "dev"
Requires-Dist: pytest-mock>=3.8.0; extra == "dev"
Requires-Dist: pyspark==3.5.1; extra == "dev"
Requires-Dist: moto>=5.0.7; extra == "dev"
Requires-Dist: black>=24.4.2; extra == "dev"
Requires-Dist: isort>=5.13.2; extra == "dev"
Requires-Dist: freezegun; extra == "dev"
Provides-Extra: doc
Requires-Dist: ons-mkdocs-theme>=1.1.3; extra == "doc"
Requires-Dist: mkdocstrings[python]>=0.22.0; extra == "doc"
Requires-Dist: mkdocs-git-revision-date-localized-plugin>=1.2.1; extra == "doc"
Requires-Dist: mkdocs-jupyter>=0.24.3; extra == "doc"
Requires-Dist: mkdocs-mermaid2-plugin>=1.1.1; extra == "doc"
Dynamic: license-file
